odoo8_addon_project_timesheet_analytic_partner-8.0.1.0.0.99.dev10-py2.7-nspkg.pth
odoo8_addon_project_timesheet_analytic_partner-8.0.1.0.0.99.dev10.dist-info/DESCRIPTION.rst
odoo8_addon_project_timesheet_analytic_partner-8.0.1.0.0.99.dev10.dist-info/METADATA
odoo8_addon_project_timesheet_analytic_partner-8.0.1.0.0.99.dev10.dist-info/RECORD
odoo8_addon_project_timesheet_analytic_partner-8.0.1.0.0.99.dev10.dist-info/WHEEL
odoo8_addon_project_timesheet_analytic_partner-8.0.1.0.0.99.dev10.dist-info/metadata.json
odoo8_addon_project_timesheet_analytic_partner-8.0.1.0.0.99.dev10.dist-info/namespace_packages.txt
odoo8_addon_project_timesheet_analytic_partner-8.0.1.0.0.99.dev10.dist-info/top_level.txt
odoo_addons/project_timesheet_analytic_partner/README.rst
odoo_addons/project_timesheet_analytic_partner/__init__.py
odoo_addons/project_timesheet_analytic_partner/__openerp__.py
odoo_addons/project_timesheet_analytic_partner/i18n/ar.po
odoo_addons/project_timesheet_analytic_partner/i18n/ca.po
odoo_addons/project_timesheet_analytic_partner/i18n/de.po
odoo_addons/project_timesheet_analytic_partner/i18n/el.po
odoo_addons/project_timesheet_analytic_partner/i18n/es.po
odoo_addons/project_timesheet_analytic_partner/i18n/es_CR.po
odoo_addons/project_timesheet_analytic_partner/i18n/es_MX.po
odoo_addons/project_timesheet_analytic_partner/i18n/es_VE.po
odoo_addons/project_timesheet_analytic_partner/i18n/fi.po
odoo_addons/project_timesheet_analytic_partner/i18n/fr.po
odoo_addons/project_timesheet_analytic_partner/i18n/gl.po
odoo_addons/project_timesheet_analytic_partner/i18n/hr.po
odoo_addons/project_timesheet_analytic_partner/i18n/hr_HR.po
odoo_addons/project_timesheet_analytic_partner/i18n/hu.po
odoo_addons/project_timesheet_analytic_partner/i18n/it.po
odoo_addons/project_timesheet_analytic_partner/i18n/ja.po
odoo_addons/project_timesheet_analytic_partner/i18n/lt.po
odoo_addons/project_timesheet_analytic_partner/i18n/lv.po
odoo_addons/project_timesheet_analytic_partner/i18n/mk.po
odoo_addons/project_timesheet_analytic_partner/i18n/mn.po
odoo_addons/project_timesheet_analytic_partner/i18n/nl.po
odoo_addons/project_timesheet_analytic_partner/i18n/pl.po
odoo_addons/project_timesheet_analytic_partner/i18n/project_timesheet_analytic_partner.pot
odoo_addons/project_timesheet_analytic_partner/i18n/pt.po
odoo_addons/project_timesheet_analytic_partner/i18n/pt_BR.po
odoo_addons/project_timesheet_analytic_partner/i18n/pt_PT.po
odoo_addons/project_timesheet_analytic_partner/i18n/ro.po
odoo_addons/project_timesheet_analytic_partner/i18n/sl.po
